LICENSE
MANIFEST.in
README.rst
setup.py
backups/__init__.py
backups/admin.py
backups/apps.py
backups/functions.py
backups/models.py
backups/tests.py
backups/urls.py
backups/views.py
backups/__pycache__/__init__.cpython-36.pyc
backups/__pycache__/admin.cpython-36.pyc
backups/__pycache__/apps.cpython-36.pyc
backups/__pycache__/functions.cpython-36.pyc
backups/__pycache__/models.cpython-36.pyc
backups/__pycache__/urls.cpython-36.pyc
backups/__pycache__/views.cpython-36.pyc
backups/migrations/__init__.py
backups/migrations/__pycache__/__init__.cpython-36.pyc
backups/templates/b2csv_base.html
backups/templates/b2csv_head.html
backups/templates/restore_csv.html
backups/templates/select_app.html
backups/templates/select_models.html
backups/templatetags/__init__.py
backups/templatetags/backup_tags.py
backups/templatetags/__pycache__/__init__.cpython-36.pyc
backups/templatetags/__pycache__/backup_tags.cpython-36.pyc
django_backup2csv.egg-info/PKG-INFO
django_backup2csv.egg-info/SOURCES.txt
django_backup2csv.egg-info/dependency_links.txt
django_backup2csv.egg-info/top_level.txt