Metadata-Version: 1.1
Name: django-backup2csv
Version: 0.6
Summary: A simple Django app to backup and restore your models data.
Home-page: https://gitlab.com/mmandrille/django-backup2csv
Author: Marcos Federico Mandrille
Author-email: mmandrille@gmail.com
License: MIT License
Platform: UNKNOWN
Classifier: Environment :: Web Environment
Classifier: Framework :: Django
Classifier: Framework :: Django :: 2.1
Classifier: Intended Audience :: Developers
Classifier: License :: OSI Approved :: MIT License
Classifier: Operating System :: OS Independent
Classifier: Programming Language :: Python
Classifier: Programming Language :: Python :: 3.5
Classifier: Programming Language :: Python :: 3.6
Classifier: Topic :: Internet :: WWW/HTTP
Classifier: Topic :: Internet :: WWW/HTTP :: Dynamic Content
